{
	"type": "minecraft:elder_guardian",
	"name": "entity.minecraft.elder_guardian",
	"name_color": "0xC8AEA3",
	"gui_scale": 1,
	"gui_x_offset": 0,
	"gui_y_offset": 0,
	"gui_z_offset": 0,
	"sim_cost": 256,
	"input": {
		"item": "hostilenetworks:prediction_matrix"
	},
	"base_drop": {
		"item": "hostilenetworks:overworld_prediction"
	},
	"fabricator_drops": [
		{
			"item": "minecraft:cod",
			"count": 24
		},
		{
			"item": "minecraft:prismarine_crystals",
			"count": 16
		},
        {
            "item": "gtceu:aluminium_dust",
            "count": 12
        },
		{
			"optional": true,
			"item": "reliquary:guardian_spike",
			"count": 2
		}
	]
}